_qwak_proto/jfml/hosting_gateway/v1/build_upload_url_pb2.py
_qwak_proto/jfml/hosting_gateway/v1/build_upload_url_pb2.pyi
_qwak_proto/jfml/hosting_gateway/v1/build_upload_url_pb2_grpc.py
_qwak_proto/jfml/hosting_gateway/v1/hosting_gateway_service_pb2.py
_qwak_proto/jfml/hosting_gateway/v1/hosting_gateway_service_pb2.pyi
_qwak_proto/jfml/hosting_gateway/v1/hosting_gateway_service_pb2_grpc.py
_qwak_proto/qwak/administration/account/v1/account_pb2.py
_qwak_proto/qwak/administration/account/v1/account_pb2.pyi
_qwak_proto/qwak/administration/account/v1/account_pb2_grpc.py
_qwak_proto/qwak/administration/account/v1/account_service_pb2.py
_qwak_proto/qwak/administration/account/v1/account_service_pb2.pyi
_qwak_proto/qwak/administration/account/v1/account_service_pb2_grpc.py
_qwak_proto/qwak/administration/account/v1/jfrog_tenant_details_pb2.py
_qwak_proto/qwak/administration/account/v1/jfrog_tenant_details_pb2.pyi
_qwak_proto/qwak/administration/account/v1/jfrog_tenant_details_pb2_grpc.py
_qwak_proto/qwak/administration/account/v1/personalization_pb2.py
_qwak_proto/qwak/administration/account/v1/personalization_pb2.pyi
_qwak_proto/qwak/administration/account/v1/personalization_pb2_grpc.py
_qwak_proto/qwak/administration/account/v1/preferences_pb2.py
_qwak_proto/qwak/administration/account/v1/preferences_pb2.pyi
_qwak_proto/qwak/administration/account/v1/preferences_pb2_grpc.py
_qwak_proto/qwak/administration/account/v1/terms_pb2.py
_qwak_proto/qwak/administration/account/v1/terms_pb2.pyi
_qwak_proto/qwak/administration/account/v1/terms_pb2_grpc.py
_qwak_proto/qwak/administration/authenticated_user/v1/authenticated_user_service_pb2.py
_qwak_proto/qwak/administration/authenticated_user/v1/authenticated_user_service_pb2.pyi
_qwak_proto/qwak/administration/authenticated_user/v1/authenticated_user_service_pb2_grpc.py
_qwak_proto/qwak/administration/authenticated_user/v1/credentials_pb2.py
_qwak_proto/qwak/administration/authenticated_user/v1/credentials_pb2.pyi
qwak_core-0.7.2.dist-info/METADATA
qwak_core-0.7.2.dist-info/WHEEL
qwak_core-0.7.2.dist-info/RECORD
